stopword/__init__.py
stopword/stopwords.txt
stopword-0.0.4.dist-info/LICENCE
stopword-0.0.4.dist-info/METADATA
stopword-0.0.4.dist-info/WHEEL
stopword-0.0.4.dist-info/top_level.txt
stopword-0.0.4.dist-info/zip-safe
stopword-0.0.4.dist-info/RECORD
